mkpy
