Metadata-Version: 1.0
Name: python-mkpy
Version: 0.0.2
Summary: A (minimalistic) build tool simmilar to make. Written in Python 3
Home-page: https://github.com/phipus/mkpy
Author: phipus
Author-email: phipuspam@gmx.ch
License: UNKNOWN
Platform: UNKNOWN
